thyroid_model_damir/__init__.py
thyroid_model_damir/create_pipeline.py
thyroid_model_damir/label_encoder.joblib
thyroid_model_damir/load_label_encoder.py
thyroid_model_damir/load_pipeline.py
thyroid_model_damir/pipeline.joblib
thyroid_model_damir/raw.csv
thyroid_model_damir/tests.py
thyroid_model_damir-0.1.0.dist-info/LICENSE
thyroid_model_damir-0.1.0.dist-info/METADATA
thyroid_model_damir-0.1.0.dist-info/WHEEL
thyroid_model_damir-0.1.0.dist-info/top_level.txt
thyroid_model_damir-0.1.0.dist-info/RECORD
