Metadata-Version: 2.1
Name: thyroid-model-damir
Version: 0.1.0
Summary: Pretrained thyroid model and pipeline for classification
Author: Damir Bogdan
Author-email: damribogdan39@gmail.com
Classifier: Programming Language :: Python :: 3
Classifier: License :: OSI Approved :: MIT License
Classifier: Operating System :: OS Independent
Requires-Python: >=3.10.6
License-File: LICENSE
Requires-Dist: numpy (==1.25.0)
Requires-Dist: scikit-learn (==1.0.2)
Requires-Dist: xgboost (==1.7.6)
Requires-Dist: pandas (==1.5.3)
Requires-Dist: joblib (==1.3.1)
Requires-Dist: pathlib
